stGCL/__init__.py
stGCL/advance_deep_graph_infomax.py
stGCL/gat_conv.py
stGCL/image_processing.py
stGCL/image_resnet50.py
stGCL/inits.py
stGCL/modules.py
stGCL/process.py
stGCL/stGCL_model.py
stGCL/train_model.py
stGCL/utils.py
stGCL/vit_model.py
stGCL-1.0.3.dist-info/LICENSE
stGCL-1.0.3.dist-info/METADATA
stGCL-1.0.3.dist-info/WHEEL
stGCL-1.0.3.dist-info/top_level.txt
stGCL-1.0.3.dist-info/RECORD
